{"lastUsed":1560239408749,"path":"C:\/Users\/alfo1-2\/jspwork","projectCount":1,"recentFiles":[{"path":"\/Tutorial\/WebContent","parentWorkspace":"C:\/Users\/alfo1-2\/jspwork","name":"list.jsp","lastModified":1560238909119,"locationURI":"file:\/C:\/Users\/alfo1-2\/jspwork\/Tutorial\/WebContent\/list.jsp"},{"path":"\/Tutorial\/WebContent","parentWorkspace":"C:\/Users\/alfo1-2\/jspwork","name":"tutorial_ResultSet2.jsp","lastModified":1560239408928,"locationURI":"file:\/C:\/Users\/alfo1-2\/jspwork\/Tutorial\/WebContent\/tutorial_ResultSet2.jsp"},{"path":"\/Tutorial\/WebContent","parentWorkspace":"C:\/Users\/alfo1-2\/jspwork","name":"tutorial_input.jsp","lastModified":1560232898679,"locationURI":"file:\/C:\/Users\/alfo1-2\/jspwork\/Tutorial\/WebContent\/tutorial_input.jsp"},{"path":"\/Tutorial\/WebContent","parentWorkspace":"C:\/Users\/alfo1-2\/jspwork","name":"input.jsp","lastModified":1560232113243,"locationURI":"file:\/C:\/Users\/alfo1-2\/jspwork\/Tutorial\/WebContent\/input.jsp"},{"path":"\/Tutorial\/WebContent","parentWorkspace":"C:\/Users\/alfo1-2\/jspwork","name":"tutorial_ResultSet.jsp","lastModified":1560239129562,"locationURI":"file:\/C:\/Users\/alfo1-2\/jspwork\/Tutorial\/WebContent\/tutorial_ResultSet.jsp"},{"path":"\/Tutorial\/WebContent","parentWorkspace":"C:\/Users\/alfo1-2\/jspwork","name":"input.html","lastModified":1560232231735,"locationURI":"file:\/C:\/Users\/alfo1-2\/jspwork\/Tutorial\/WebContent\/input.html"}]}